lib/DecimScanner.py
lib/__init__.py
DecimScanner-1.3.1.dist-info/LICENSE.txt
DecimScanner-1.3.1.dist-info/METADATA
DecimScanner-1.3.1.dist-info/WHEEL
DecimScanner-1.3.1.dist-info/top_level.txt
DecimScanner-1.3.1.dist-info/RECORD
