Metadata-Version: 2.1
Name: DecimScanner
Version: 1.3.1
Summary: A threaded scanner package for python
Home-page: https://github.com/Cinnamon1212/
Author: Cinnamon1212
License: UNKNOWN
Keywords: python,threaded scanners,TCP,UDP,ICMP,Penetration testing,pentesting,scapy
Platform: UNKNOWN
Classifier: Development Status :: 4 - Beta
Classifier: Intended Audience :: Developers
Classifier: Programming Language :: Python :: 3
Classifier: License :: OSI Approved :: GNU General Public License v3 (GPLv3)
Classifier: Operating System :: Unix
Requires-Dist: bs4
Requires-Dist: pybluez
Requires-Dist: scapy
